arcflash/__init__.py
arcflash/afserial.py
arcflash/arcflash_pb2.py
arcflash/bootloader.bin
arcflash/main.py
arcflash/rombuild.py
arcflash/uploader.py
arcflash-0.1.3.dist-info/LICENSE
arcflash-0.1.3.dist-info/METADATA
arcflash-0.1.3.dist-info/WHEEL
arcflash-0.1.3.dist-info/entry_points.txt
arcflash-0.1.3.dist-info/top_level.txt
arcflash-0.1.3.dist-info/RECORD
