Metadata-Version: 2.1
Name: arcflash
Version: 0.1.3
Summary: Python support libraries for Arcflash flash ROM board for Acorn computers
Home-page: https://github.com/google/myelin-acorn-electron-hardware/tree/master/a3000_rom_emulator/python_lib
Author: Phillip Pearson
Author-email: pp@myelin.nz
License: UNKNOWN
Platform: UNKNOWN
Classifier: Programming Language :: Python :: 3
Classifier: License :: OSI Approved :: Apache Software License
Classifier: Operating System :: OS Independent
Requires-Dist: protobuf
Requires-Dist: PySerial
